tutorial_runner/__init__.py
tutorial_runner/__main__.py
tutorial_runner/cli.py
tutorial_runner/state.py
tutorial_runner-0.2.7.dist-info/AUTHORS.rst
tutorial_runner-0.2.7.dist-info/LICENSE
tutorial_runner-0.2.7.dist-info/METADATA
tutorial_runner-0.2.7.dist-info/WHEEL
tutorial_runner-0.2.7.dist-info/entry_points.txt
tutorial_runner-0.2.7.dist-info/top_level.txt
tutorial_runner-0.2.7.dist-info/RECORD
