Metadata-Version: 2.1
Name: tutorial-runner
Version: 0.2.7
Summary: A command line interface for running tutorial lessons.
Home-page: https://github.com/tylerdave/tutorial-runner
Author: Dave Forgac
Author-email: tylerdave@tylerdave.com
License: MPL 2.0
Keywords: tutorial_runner
Platform: UNKNOWN
Classifier: Development Status :: 2 - Pre-Alpha
Classifier: Intended Audience :: Developers
Classifier: License :: OSI Approved :: Mozilla Public License 2.0 (MPL 2.0)
Classifier: Natural Language :: English
Classifier: Programming Language :: Python :: 3
Classifier: Programming Language :: Python :: 3.5
Classifier: Programming Language :: Python :: 3.6
Classifier: Programming Language :: Python :: 3.7
Requires-Dist: Click (>=6.0)
Requires-Dist: pytoml
Requires-Dist: pytest (>=3.5.0)
Requires-Dist: pytest-clarity
